channels_graphql_ws/__init__.py
channels_graphql_ws/client.py
channels_graphql_ws/dict_as_object.py
channels_graphql_ws/graphql_ws_consumer.py
channels_graphql_ws/serializer.py
channels_graphql_ws/subscription.py
channels_graphql_ws/testing.py
channels_graphql_ws/transport.py
baseapp_django_channels_graphql_ws-1.0.0rc9.dist-info/LICENSE
baseapp_django_channels_graphql_ws-1.0.0rc9.dist-info/METADATA
baseapp_django_channels_graphql_ws-1.0.0rc9.dist-info/WHEEL
baseapp_django_channels_graphql_ws-1.0.0rc9.dist-info/RECORD
